uzbek_language/__init__.py
uzbek_language/transliterate.py
uzbek_language/uzwords.py
uzbek_language/uzwords_latin.py
uzbek_language-0.1.0.dist-info/LICENSE
uzbek_language-0.1.0.dist-info/METADATA
uzbek_language-0.1.0.dist-info/WHEEL
uzbek_language-0.1.0.dist-info/top_level.txt
uzbek_language-0.1.0.dist-info/RECORD
