Metadata-Version: 2.1
Name: uzbek-language
Version: 0.1.0
Summary: This package was created to correct Uzbek spelling mistakes and translate from Latin to Cyrillic
Home-page: https://github.com/QuvonchbekBobojonov/Uzbek-language
Author: Quvonchbek Bobojonov
Author-email: moorfoinfo@gmail.com
Classifier: Development Status :: 3 - Alpha
Classifier: Intended Audience :: Developers
Classifier: License :: OSI Approved :: MIT License
Classifier: Programming Language :: Python :: 3
Classifier: Programming Language :: Python :: 3.6
Classifier: Programming Language :: Python :: 3.7
Classifier: Programming Language :: Python :: 3.8
Classifier: Programming Language :: Python :: 3.9
Classifier: Programming Language :: Python :: 3.10
Classifier: Programming Language :: Python :: 3.11
License-File: LICENSE
